gcode_receiver/__init__.py
gcode_receiver/cmdline.py
gcode_receiver/commands.py
gcode_receiver/receiver.py
gcode_receiver/responses.py
gcode_receiver/worker.py
gcode_receiver-1.0.2.dist-info/METADATA
gcode_receiver-1.0.2.dist-info/WHEEL
gcode_receiver-1.0.2.dist-info/entry_points.txt
gcode_receiver-1.0.2.dist-info/top_level.txt
gcode_receiver-1.0.2.dist-info/RECORD
